poetry_demo_semapu/__init__.py
poetry_demo_semapu/api.py
poetry_demo_semapu-0.1.0.dist-info/METADATA
poetry_demo_semapu-0.1.0.dist-info/WHEEL
poetry_demo_semapu-0.1.0.dist-info/RECORD
